detectadvprompt/__init__.py
detectadvprompt/api.py
detectadvprompt/dp.py
detectadvprompt/utils.py
detectadvprompt-0.1.1.dist-info/METADATA
detectadvprompt-0.1.1.dist-info/WHEEL
detectadvprompt-0.1.1.dist-info/RECORD
