Metadata-Version: 2.1
Name: detectadvprompt
Version: 0.1.1
Summary: Token level detection of adversarial prompt. 
Author: Zhengmian Hu
Author-email: huzhengmian@gmail.com
Requires-Python: >=3.9,<3.13
Classifier: Programming Language :: Python :: 3
Classifier: Programming Language :: Python :: 3.9
Classifier: Programming Language :: Python :: 3.10
Classifier: Programming Language :: Python :: 3.11
Requires-Dist: numpy (>=1.20.0,<2.0.0)
Requires-Dist: scipy (>=1.11.3,<2.0.0)
Requires-Dist: torch (>=2.0.0,!=2.0.1,!=2.1.0)
Requires-Dist: transformers (>=4.34.1,<5.0.0)
